ai_kill_switch/__init__.py
ai_kill_switch/core.py
ai_kill_switch-0.0.1.dist-info/licenses/LICENSE
ai_kill_switch-0.0.1.dist-info/METADATA
ai_kill_switch-0.0.1.dist-info/WHEEL
ai_kill_switch-0.0.1.dist-info/top_level.txt
ai_kill_switch-0.0.1.dist-info/RECORD
