Metadata-Version: 2.4
Name: ai-kill-switch
Version: 0.0.1
Summary: AI Kill Switch SDK
Home-page: https://github.com/ai-kill-switch/ai-kill-switch
Author: AI Kill Switch Team
Author-email: AI Kill Switch Team <ai.kill.switch.contact@gmail.com>
Maintainer-email: AI Kill Switch Team <ai.kill.switch.contact@gmail.com>
License: MIT
Project-URL: Homepage, https://ai-kill-switch.github.io
Project-URL: Repository, https://github.com/ai-kill-switch/ai-kill-switch
Project-URL: Documentation, https://ai-kill-switch.github.io
Project-URL: Issues, https://github.com/ai-kill-switch/ai-kill-switch/issues
Keywords: ai,kill-switch,sdk,safety
Classifier: Development Status :: 3 - Alpha
Classifier: Intended Audience :: Developers
Classifier: License :: OSI Approved :: MIT License
Classifier: Operating System :: OS Independent
Classifier: Programming Language :: Python :: 3
Classifier: Programming Language :: Python :: 3.7
Classifier: Programming Language :: Python :: 3.8
Classifier: Programming Language :: Python :: 3.9
Classifier: Programming Language :: Python :: 3.10
Classifier: Programming Language :: Python :: 3.11
Classifier: Programming Language :: Python :: 3.12
Requires-Python: >=3.7
License-File: LICENSE
Provides-Extra: dev
Requires-Dist: pytest>=6.0; extra == "dev"
Requires-Dist: pytest-cov>=2.0; extra == "dev"
Requires-Dist: black>=21.0; extra == "dev"
Requires-Dist: flake8>=3.8; extra == "dev"
Requires-Dist: mypy>=0.800; extra == "dev"
Dynamic: author
Dynamic: home-page
Dynamic: license-file
Dynamic: requires-python
